glenv/__init__.py
glenv/__main__.py
glenv/cli.py
glenv/glenv.py
glenv/log.py
glenv/managers/__init__.py
glenv/managers/base.py
glenv/managers/dotenv.py
glenv/managers/exceptions.py
glenv/managers/gitlab.py
glenv/managers/terraform.py
glenv/managers/utils.py
glenv/types/__init__.py
glenv/types/formats.py
glenv/types/variable.py
glenv-0.1.0.dist-info/entry_points.txt
glenv-0.1.0.dist-info/WHEEL
glenv-0.1.0.dist-info/METADATA
glenv-0.1.0.dist-info/RECORD
